tts_wrapper/__init__.py
tts_wrapper/exceptions.py
tts_wrapper/language_utils.py
tts_wrapper/preinstall.py
tts_wrapper/pyinstaller_utils.py
tts_wrapper/tts.py
tts_wrapper/_pyinstaller/hook-sounddevice.py
tts_wrapper/_pyinstaller/hook-tts_wrapper.py
tts_wrapper/engines/__init__.py
tts_wrapper/engines/utils.py
tts_wrapper/engines/avsynth/Package.resolved
tts_wrapper/engines/avsynth/Package.swift
tts_wrapper/engines/avsynth/SpeechBridge
tts_wrapper/engines/avsynth/SpeechBridge.dylib
tts_wrapper/engines/avsynth/SpeechBridge.py
tts_wrapper/engines/avsynth/__init__.py
tts_wrapper/engines/avsynth/build-lib.sh
tts_wrapper/engines/avsynth/client.py
tts_wrapper/engines/avsynth/setup.py
tts_wrapper/engines/avsynth/ssml.py
tts_wrapper/engines/avsynth/Sources/main.swift
tts_wrapper/engines/avsynth/Sources/SpeechBridge/main.swift
tts_wrapper/engines/elevenlabs/__init__.py
tts_wrapper/engines/elevenlabs/client.py
tts_wrapper/engines/elevenlabs/ssml.py
tts_wrapper/engines/espeak/__init__.py
tts_wrapper/engines/espeak/_espeak.py
tts_wrapper/engines/espeak/client.py
tts_wrapper/engines/espeak/ssml.py
tts_wrapper/engines/google/__init__.py
tts_wrapper/engines/google/client.py
tts_wrapper/engines/google/ssml.py
tts_wrapper/engines/googletrans/__init__.py
tts_wrapper/engines/googletrans/client.py
tts_wrapper/engines/googletrans/ssml.py
tts_wrapper/engines/microsoft/__init__.py
tts_wrapper/engines/microsoft/client.py
tts_wrapper/engines/microsoft/ssml.py
tts_wrapper/engines/mms/__init__.py
tts_wrapper/engines/mms/client.py
tts_wrapper/engines/mms/mms.py
tts_wrapper/engines/mms/ssml.py
tts_wrapper/engines/openai/__init__.py
tts_wrapper/engines/openai/client.py
tts_wrapper/engines/openai/ssml.py
tts_wrapper/engines/pico/__init__.py
tts_wrapper/engines/pico/client.py
tts_wrapper/engines/pico/pico.py
tts_wrapper/engines/piper/__init__.py
tts_wrapper/engines/piper/client.py
tts_wrapper/engines/piper/piper.py
tts_wrapper/engines/piper/ssml.py
tts_wrapper/engines/playht/__init__.py
py3_tts_wrapper-0.10.22.dist-info/METADATA
py3_tts_wrapper-0.10.22.dist-info/WHEEL
py3_tts_wrapper-0.10.22.dist-info/entry_points.txt
py3_tts_wrapper-0.10.22.dist-info/licenses/LICENSE
py3_tts_wrapper-0.10.22.dist-info/RECORD
