Metadata-Version: 2.4
Name: py3-tts-wrapper
Version: 0.10.22
Summary: TTS-Wrapper makes it easier to use text-to-speech APIs by providing a unified and easy-to-use interface.
Project-URL: Bug Tracker, https://github.com/willwade/tts-wrapper/issues
Author-email: Will Wade <willwade@gmail.com>, Giulio Bottari <giuliobottari@gmail.com>
License-Expression: MIT
License-File: LICENSE
Keywords: elevenlabs,gTTS,mms,playht,polly,sapi,sherpaonnx,speech synthesis,text-to-speech,tts,upliftai,witai
Requires-Python: <3.13,>=3.10
Requires-Dist: langcodes
Requires-Dist: language-data>=1.3.0
Requires-Dist: marisa-trie>=1.2.1
Requires-Dist: numpy>=1.24.3
Requires-Dist: pymp3>=0.2.0
Requires-Dist: requests>=2.31.0
Requires-Dist: sounddevice>=0.5.0
Requires-Dist: soundfile>=0.12.1
Provides-Extra: avsynth
Provides-Extra: controlaudio
Requires-Dist: pyaudio>=0.2.14; extra == 'controlaudio'
Provides-Extra: elevenlabs
Provides-Extra: espeak
Provides-Extra: google
Requires-Dist: google-cloud-texttospeech>=2.12.0; extra == 'google'
Provides-Extra: googletrans
Requires-Dist: gtts>=2.5.2; extra == 'googletrans'
Provides-Extra: microsoft
Requires-Dist: azure-cognitiveservices-speech>=1.43.0; extra == 'microsoft'
Provides-Extra: openai
Requires-Dist: openai; extra == 'openai'
Provides-Extra: playht
Provides-Extra: polly
Requires-Dist: boto3>=1.34.137; extra == 'polly'
Provides-Extra: sapi
Requires-Dist: comtypes>=1.4.11; extra == 'sapi'
Requires-Dist: comtypes>=1.4.11; (sys_platform == 'win32') and extra == 'sapi'
Provides-Extra: sherpaonnx
Requires-Dist: sherpa-onnx<1.11.7,>=1.10.17; extra == 'sherpaonnx'
Provides-Extra: uwp
Requires-Dist: winrt-runtime>=2.0.1; (sys_platform == 'win32') and extra == 'uwp'
Provides-Extra: watson
Requires-Dist: ibm-watson>=8.1.0; extra == 'watson'
Requires-Dist: websocket-client; extra == 'watson'
Provides-Extra: witai
